visual_selection/__init__.py
visual_selection/__main__.py
visual_selection/app.py
visual_selection-1.0.0.dist-info/METADATA
visual_selection-1.0.0.dist-info/WHEEL
visual_selection-1.0.0.dist-info/entry_points.txt
visual_selection-1.0.0.dist-info/licenses/LICENSE
visual_selection-1.0.0.dist-info/RECORD
