Metadata-Version: 2.3
Name: visual-selection
Version: 1.0.0
Summary: A simple illustration of mutation aiding evolution
Author-email: Dave Pearson <davep@davep.org>
License: GNU General Public License v3 or later (GPLv3+)
Keywords: evolution,example,illustration,science
Classifier: Development Status :: 3 - Alpha
Classifier: Environment :: Console
Classifier: License :: OSI Approved :: GNU General Public License v3 or later (GPLv3+)
Classifier: Operating System :: OS Independent
Classifier: Programming Language :: Python :: 3.8
Classifier: Programming Language :: Python :: 3.9
Classifier: Programming Language :: Python :: 3.10
Classifier: Programming Language :: Python :: 3.11
Classifier: Programming Language :: Python :: 3.12
Classifier: Topic :: Terminals
Classifier: Typing :: Typed
Requires-Python: >=3.10
Requires-Dist: textual-plotext>=0.2.1
Requires-Dist: textual>=3.3.0
